aes_encryption/__init__.py
aes_encryption/main.py
aes_encryption-0.2.0.dist-info/LICENSE
aes_encryption-0.2.0.dist-info/METADATA
aes_encryption-0.2.0.dist-info/WHEEL
aes_encryption-0.2.0.dist-info/top_level.txt
aes_encryption-0.2.0.dist-info/RECORD
