Metadata-Version: 2.1
Name: aes-encryption
Version: 0.2.0
Summary: An AES encryption package
Home-page: https://github.com/apinanyogaratnam/aes-encryption
Author: apinanyogaratnam
Author-email: apinanapinan@icloud.com
Classifier: Programming Language :: Python :: 3
Classifier: License :: OSI Approved :: MIT License
Classifier: Operating System :: OS Independent
Requires-Python: >=3.10.4
License-File: LICENSE
Requires-Dist: pycryptodome
